ragnardoc/.coveragerc
ragnardoc/__main__.py
ragnardoc/_version.py
ragnardoc/core.py
ragnardoc/factory.py
ragnardoc/scraping.py
ragnardoc/types.py
ragnardoc/cli/__init__.py
ragnardoc/cli/add.py
ragnardoc/cli/base.py
ragnardoc/cli/common.py
ragnardoc/cli/run.py
ragnardoc/cli/start.py
ragnardoc/cli/init/__init__.py
ragnardoc/cli/init/anything_llm_initializer.py
ragnardoc/cli/init/init_command.py
ragnardoc/cli/init/initializer_base.py
ragnardoc/cli/init/open_webui_initializer.py
ragnardoc/config/__init__.py
ragnardoc/config/config.yaml
ragnardoc/config/merge.py
ragnardoc/ingestors/__init__.py
ragnardoc/ingestors/anything_llm.py
ragnardoc/ingestors/base.py
ragnardoc/ingestors/open_webui.py
ragnardoc/storage/__init__.py
ragnardoc/storage/base.py
ragnardoc/storage/dict_storage.py
ragnardoc/storage/sqlite_storage.py
ragnardoc-0.1.1.dist-info/LICENSE
ragnardoc-0.1.1.dist-info/METADATA
ragnardoc-0.1.1.dist-info/WHEEL
ragnardoc-0.1.1.dist-info/entry_points.txt
ragnardoc-0.1.1.dist-info/top_level.txt
ragnardoc-0.1.1.dist-info/RECORD
