Metadata-Version: 2.2
Name: ragnardoc
Version: 0.1.1
Summary: RAGNARDoc (RAG Native Automatic Reingestion for Documents) is a tool that runs natively on a developer workstation and automatically ingests local documents into various Retrieval Augmented Generation indexes. It is designed as a companion app for workstation RAG applications which would benefit from maintaining an up-to-date view of documents hosted natively on a user's workstation.
License: Apache-2.0
Project-URL: Source, https://github.com/DS4SD/ragnardoc
Classifier: License :: OSI Approved :: Apache Software License
Requires-Python: >=3.11
License-File: LICENSE
Requires-Dist: alchemy-config<2,>=1.1.3
Requires-Dist: alchemy-logging<2,>=1.5
Requires-Dist: docling<3,>=2.14.0
Requires-Dist: requests<3,>=2.32.3
Requires-Dist: jsonschema<5,>=4.23.0
Provides-Extra: dev-test
Requires-Dist: pytest-cov<6.0,>=2.10.1; extra == "dev-test"
Requires-Dist: pytest-html<5.0,>=3.1.1; extra == "dev-test"
Requires-Dist: pytest<8.0,>=6.2.5; extra == "dev-test"
Requires-Dist: wheel>=0.38.4; extra == "dev-test"
Provides-Extra: dev-fmt
Requires-Dist: ruff==0.4.7; extra == "dev-fmt"
Requires-Dist: pre-commit<4.0,>=3.0.4; extra == "dev-fmt"
Provides-Extra: dev-build
Requires-Dist: build; extra == "dev-build"
Requires-Dist: twine; extra == "dev-build"
Provides-Extra: all
Requires-Dist: ragnardoc[dev-build,dev-fmt,dev-test]; extra == "all"
